langextract_provider_litellm/__init__.py
langextract_provider_litellm/provider.py
langextract_provider_litellm-0.1.1.dist-info/licenses/LICENSE
langextract_provider_litellm-0.1.1.dist-info/METADATA
langextract_provider_litellm-0.1.1.dist-info/WHEEL
langextract_provider_litellm-0.1.1.dist-info/entry_points.txt
langextract_provider_litellm-0.1.1.dist-info/top_level.txt
langextract_provider_litellm-0.1.1.dist-info/RECORD
